xw_customer.cpython-39-x86_64-linux-gnu.so
xw_customer-16.0.0.2.dist-info/RECORD
xw_customer-16.0.0.2.dist-info/LICENSE
xw_customer-16.0.0.2.dist-info/WHEEL
xw_customer-16.0.0.2.dist-info/METADATA
xw_customer-16.0.0.2.dist-info/top_level.txt
