Metadata-Version: 2.1
Name: xw-customer
Version: 16.0.0.2
Summary: utils for xw customer
Home-page: https://www.openerpenext.com/
Author: xw odoo
Author-email: 2243879204@qq.com
Requires-Python: >=3.7
License-File: LICENSE
